{
  "$schema": "https://schema.management.azure.com/schemas/2015-01-01/deploymentParameters.json#",
  "contentVersion": "1.0.0.0",
  "parameters": {
    "resourceName": {
      "value": "brg-pot-sql"
    },
    "tags": {
      "value": {
        "author": "p.moramarco@reply.it"
      }
    },
    "firewallExceptions": {
      "value": [
        {
          "name": "reply-91-226-5",
          "address": "91.218.226.5"
        },
        {
          "name": "reply-91-226-15",
          "address": "91.218.226.15"
        },
        {
          "name": "reply-91-224-5",
          "address": "91.218.224.5"
        },
        {
          "name": "reply-91-224-15",
          "address": "91.218.224.15"
        }
      ]
    }
  }
}